{
"id": "basketball-w",
"updatedAt": "2026-04-01",
"entries": [
{"rank":1,"code":"USA","name":"USA","points":719.1,"prevRank":1},
{"rank":2,"code":"FRA","name":"France","points":596.6,"prevRank":2},
{"rank":3,"code":"AUS","name":"Australia","points":596.4,"prevRank":3},
{"rank":4,"code":"CHN","name":"China","points":585.8,"prevRank":4},
{"rank":5,"code":"BEL","name":"Belgium","points":585.5,"prevRank":5},
{"rank":6,"code":"ESP","name":"Spain","points":574.2,"prevRank":6},
{"rank":7,"code":"CAN","name":"Canada","points":541.5,"prevRank":7},
{"rank":8,"code":"NGR","name":"Nigeria","points":525.2,"prevRank":8},
{"rank":9,"code":"BRA","name":"Brazil","points":522.9,"prevRank":9},
{"rank":10,"code":"JPN","name":"Japan","points":505.1,"prevRank":10},
{"rank":11,"code":"GER","name":"Germany","points":504.8,"prevRank":11},
{"rank":12,"code":"SRB","name":"Serbia","points":471.7,"prevRank":12},
{"rank":13,"code":"PUR","name":"Puerto Rico","points":445.5,"prevRank":13},
{"rank":14,"code":"ITA","name":"Italy","points":412.6,"prevRank":14},
{"rank":15,"code":"KOR","name":"Korea","points":405.5,"prevRank":15},
{"rank":16,"code":"TUR","name":"Türkiye","points":338.8,"prevRank":16},
{"rank":17,"code":"CZE","name":"Czechia","points":337.3,"prevRank":17},
{"rank":18,"code":"MLI","name":"Mali","points":302.4,"prevRank":18},
{"rank":19,"code":"HUN","name":"Hungary","points":293.5,"prevRank":19},
{"rank":20,"code":"COL","name":"Colombia","points":286.2,"prevRank":20},
{"rank":21,"code":"NZL","name":"New Zealand","points":280.6,"prevRank":21},
{"rank":22,"code":"SEN","name":"Senegal","points":263,"prevRank":22},
{"rank":23,"code":"ARG","name":"Argentina","points":261.8,"prevRank":23},
{"rank":24,"code":"GBR","name":"Great Britain","points":244.8,"prevRank":24},
{"rank":25,"code":"SLO","name":"Slovenia","points":242.1,"prevRank":25},
{"rank":26,"code":"MNE","name":"Montenegro","points":242,"prevRank":26},
{"rank":27,"code":"GRE","name":"Greece","points":234,"prevRank":27},
{"rank":28,"code":"BIH","name":"Bosnia and Herzegovina","points":215.2,"prevRank":28},
{"rank":29,"code":"SWE","name":"Sweden","points":214.7,"prevRank":29},
{"rank":30,"code":"PHI","name":"Philippines","points":194.9,"prevRank":30},
{"rank":31,"code":"MEX","name":"Mexico","points":193.5,"prevRank":31},
{"rank":32,"code":"SVK","name":"Slovakia","points":185.5,"prevRank":32},
{"rank":33,"code":"LTU","name":"Lithuania","points":183.6,"prevRank":33},
{"rank":34,"code":"MOZ","name":"Mozambique","points":179.4,"prevRank":34},
{"rank":35,"code":"LAT","name":"Latvia","points":176.5,"prevRank":35},
{"rank":36,"code":"DOM","name":"Dominican Republic","points":171.8,"prevRank":36},
{"rank":37,"code":"CMR","name":"Cameroon","points":168.2,"prevRank":37},
{"rank":38,"code":"CRO","name":"Croatia","points":167.5,"prevRank":38},
{"rank":39,"code":"TPE","name":"Chinese Taipei","points":166.2,"prevRank":39},
{"rank":40,"code":"POR","name":"Portugal","points":165.6,"prevRank":40},
{"rank":41,"code":"UKR","name":"Ukraine","points":154,"prevRank":41},
{"rank":42,"code":"SSD","name":"South Sudan","points":151,"prevRank":42},
{"rank":43,"code":"POL","name":"Poland","points":148.8,"prevRank":43},
{"rank":44,"code":"LBN","name":"Lebanon","points":143.5,"prevRank":44},
{"rank":45,"code":"EGY","name":"Egypt","points":139,"prevRank":45},
{"rank":46,"code":"SUI","name":"Switzerland","points":137.8,"prevRank":46},
{"rank":47,"code":"IRI","name":"Iran","points":136.9,"prevRank":47},
{"rank":48,"code":"ISR","name":"Israel","points":133.7,"prevRank":48},
{"rank":49,"code":"VEN","name":"Venezuela","points":130.3,"prevRank":49},
{"rank":50,"code":"CUB","name":"Cuba","points":127.1,"prevRank":50},
{"rank":51,"code":"ESA","name":"El Salvador","points":126,"prevRank":51},
{"rank":52,"code":"LUX","name":"Luxembourg","points":125.9,"prevRank":52},
{"rank":53,"code":"CIV","name":"Cote d'Ivoire","points":123.2,"prevRank":53},
{"rank":54,"code":"NED","name":"Netherlands","points":121.3,"prevRank":54},
{"rank":55,"code":"ANG","name":"Angola","points":120.2,"prevRank":55},
{"rank":56,"code":"DEN","name":"Denmark","points":118.1,"prevRank":56},
{"rank":57,"code":"UGA","name":"Uganda","points":114.6,"prevRank":57},
{"rank":58,"code":"BUL","name":"Bulgaria","points":114.3,"prevRank":58},
{"rank":59,"code":"INA","name":"Indonesia","points":107.8,"prevRank":59},
{"rank":60,"code":"ROU","name":"Romania","points":106.2,"prevRank":60},
{"rank":61,"code":"THA","name":"Thailand","points":105.5,"prevRank":61},
{"rank":62,"code":"IND","name":"India","points":102.5,"prevRank":62},
{"rank":63,"code":"ISL","name":"Iceland","points":98.7,"prevRank":63},
{"rank":64,"code":"ISV","name":"Virgin Islands","points":96.3,"prevRank":64},
{"rank":65,"code":"NOR","name":"Norway","points":96,"prevRank":65},
{"rank":66,"code":"FIN","name":"Finland","points":92.8,"prevRank":66},
{"rank":67,"code":"EST","name":"Estonia","points":92.8,"prevRank":67},
{"rank":68,"code":"JOR","name":"Jordan","points":90.3,"prevRank":68},
{"rank":69,"code":"KAZ","name":"Kazakhstan","points":86.3,"prevRank":69},
{"rank":70,"code":"MKD","name":"North Macedonia","points":84.7,"prevRank":70},
{"rank":71,"code":"CHI","name":"Chile","points":84.1,"prevRank":71},
{"rank":72,"code":"MGL","name":"Mongolia","points":84,"prevRank":72},
{"rank":73,"code":"AUT","name":"Austria","points":81.3,"prevRank":73},
{"rank":74,"code":"RWA","name":"Rwanda","points":81.1,"prevRank":74},
{"rank":75,"code":"PAR","name":"Paraguay","points":80.6,"prevRank":75},
{"rank":76,"code":"CYP","name":"Cyprus","points":79.8,"prevRank":76},
{"rank":77,"code":"IRL","name":"Ireland","points":78.3,"prevRank":77},
{"rank":78,"code":"GUA","name":"Guatemala","points":76.9,"prevRank":78},
{"rank":79,"code":"CRC","name":"Costa Rica","points":76.6,"prevRank":79},
{"rank":80,"code":"MAS","name":"Malaysia","points":75.4,"prevRank":80},
{"rank":81,"code":"KEN","name":"Kenya","points":73.5,"prevRank":81},
{"rank":82,"code":"MLT","name":"Malta","points":72.3,"prevRank":82},
{"rank":83,"code":"COD","name":"Congo DR","points":70.1,"prevRank":83},
{"rank":84,"code":"SYR","name":"Syria","points":61,"prevRank":84},
{"rank":85,"code":"KOS","name":"Kosovo","points":60.9,"prevRank":85},
{"rank":86,"code":"ECU","name":"Ecuador","points":59.7,"prevRank":86},
{"rank":87,"code":"BAH","name":"Bahamas","points":58.5,"prevRank":87},
{"rank":88,"code":"ARM","name":"Armenia","points":57,"prevRank":88},
{"rank":89,"code":"UZB","name":"Uzbekistan","points":56.3,"prevRank":89},
{"rank":90,"code":"ALB","name":"Albania","points":55.5,"prevRank":90},
{"rank":91,"code":"NCA","name":"Nicaragua","points":54.1,"prevRank":91},
{"rank":92,"code":"BOL","name":"Bolivia","points":53,"prevRank":92},
{"rank":93,"code":"AZE","name":"Azerbaijan","points":52.8,"prevRank":93},
{"rank":94,"code":"BAR","name":"Barbados","points":52.1,"prevRank":94},
{"rank":95,"code":"GUI","name":"Guinea","points":50.9,"prevRank":95},
{"rank":96,"code":"PAN","name":"Panama","points":50.3,"prevRank":96},
{"rank":97,"code":"URU","name":"Uruguay","points":49.5,"prevRank":97},
{"rank":98,"code":"HON","name":"Honduras","points":48.9,"prevRank":98},
{"rank":99,"code":"CPV","name":"Cape Verde","points":46.5,"prevRank":99},
{"rank":100,"code":"ZIM","name":"Zimbabwe","points":45.8,"prevRank":100},
{"rank":101,"code":"COK","name":"Cook Islands","points":45.5,"prevRank":101},
{"rank":102,"code":"TUN","name":"Tunisia","points":44.7,"prevRank":102},
{"rank":103,"code":"VIN","name":"St.Vincent and the Grenadines","points":42.5,"prevRank":103},
{"rank":104,"code":"MDV","name":"Maldives","points":39.5,"prevRank":104},
{"rank":105,"code":"HKG","name":"Hong Kong, China","points":38.2,"prevRank":105},
{"rank":106,"code":"AND","name":"Andorra","points":38.1,"prevRank":106},
{"rank":107,"code":"MDA","name":"Moldova","points":35.8,"prevRank":107},
{"rank":108,"code":"SUR","name":"Suriname","points":35.3,"prevRank":108},
{"rank":109,"code":"JAM","name":"Jamaica","points":32.5,"prevRank":109},
{"rank":110,"code":"NEP","name":"Nepal","points":32,"prevRank":110},
{"rank":111,"code":"GIB","name":"Gibraltar","points":29.5,"prevRank":111},
{"rank":112,"code":"ZAM","name":"Zambia","points":27.9,"prevRank":112},
{"rank":113,"code":"BDI","name":"Burundi","points":25.3,"prevRank":113},
{"rank":114,"code":"TAH","name":"Tahiti","points":24.8,"prevRank":114},
{"rank":115,"code":"SRI","name":"Sri Lanka","points":24.1,"prevRank":115},
{"rank":116,"code":"KGZ","name":"Kyrgyzstan","points":22.4,"prevRank":116},
{"rank":117,"code":"GAB","name":"Gabon","points":20.8,"prevRank":117},
{"rank":118,"code":"GUY","name":"Guyana","points":19.6,"prevRank":118},
{"rank":119,"code":"GEO","name":"Georgia","points":19.5,"prevRank":119}
]
}
